officeintegrator/__init__.py
officeintegrator/src/__init__.py
officeintegrator/src/json_details.json
officeintegrator/src/com/__init__.py
officeintegrator/src/com/zoho/__init__.py
officeintegrator/src/com/zoho/api/__init__.py
officeintegrator/src/com/zoho/api/authenticator/__init__.py
officeintegrator/src/com/zoho/api/authenticator/auth.py
officeintegrator/src/com/zoho/api/authenticator/authentication_schema.py
officeintegrator/src/com/zoho/api/authenticator/oauth2.py
officeintegrator/src/com/zoho/api/authenticator/parsable_enum.py
officeintegrator/src/com/zoho/api/authenticator/token.py
officeintegrator/src/com/zoho/api/authenticator/store/__init__.py
officeintegrator/src/com/zoho/api/authenticator/store/db_store.py
officeintegrator/src/com/zoho/api/authenticator/store/file_store.py
officeintegrator/src/com/zoho/api/authenticator/store/token_store.py
officeintegrator/src/com/zoho/officeintegrator/__init__.py
officeintegrator/src/com/zoho/officeintegrator/header.py
officeintegrator/src/com/zoho/officeintegrator/header_map.py
officeintegrator/src/com/zoho/officeintegrator/initializer.py
officeintegrator/src/com/zoho/officeintegrator/param.py
officeintegrator/src/com/zoho/officeintegrator/parameter_map.py
officeintegrator/src/com/zoho/officeintegrator/request_proxy.py
officeintegrator/src/com/zoho/officeintegrator/sdk_config.py
officeintegrator/src/com/zoho/officeintegrator/user_signature.py
officeintegrator/src/com/zoho/officeintegrator/dc/__init__.py
officeintegrator/src/com/zoho/officeintegrator/dc/data_center.py
officeintegrator/src/com/zoho/officeintegrator/dc/environment.py
officeintegrator/src/com/zoho/officeintegrator/exception/__init__.py
officeintegrator/src/com/zoho/officeintegrator/exception/sdk_exception.py
officeintegrator/src/com/zoho/officeintegrator/logger/__init__.py
officeintegrator/src/com/zoho/officeintegrator/logger/logger.py
officeintegrator/src/com/zoho/officeintegrator/util/__init__.py
office_integrator_sdk-1.0.2.dist-info/LICENSE
office_integrator_sdk-1.0.2.dist-info/METADATA
office_integrator_sdk-1.0.2.dist-info/WHEEL
office_integrator_sdk-1.0.2.dist-info/top_level.txt
office_integrator_sdk-1.0.2.dist-info/RECORD
